safearena/__init__.py
safearena/config.py
safearena/modeling.py
safearena/register.py
safearena/task.py
safearena/version.py
safearena-0.1.0.dist-info/METADATA
safearena-0.1.0.dist-info/WHEEL
safearena-0.1.0.dist-info/top_level.txt
safearena-0.1.0.dist-info/RECORD
