Metadata-Version: 2.2
Name: safearena
Version: 0.1.0
Summary: SafeArena is a benchmark for agent safety
Author-email: SafeArena Team <safearena@googlegroups.com>
Project-URL: Homepage, https://safearena.github.io
Project-URL: Repository, https://github.com/mcgill-nlp/safearena
Requires-Python: >=3.10
Requires-Dist: browsergym
Requires-Dist: libwebarena
Requires-Dist: playwright
Requires-Dist: agentlab
Provides-Extra: dev
Requires-Dist: black; extra == "dev"
Requires-Dist: twine; extra == "dev"
Requires-Dist: setuptools; extra == "dev"
